radproc/__init__.py
radproc/api.py
radproc/arcgis.py
radproc/core.py
radproc/dwd_gauge.py
radproc/heavyrain.py
radproc/raw.py
radproc/version.py
radproc/wradlib_io.py
radproc/sampledata/__init__.py
radproc/sampledata/radolan_proj.prj
radproc-0.1.4.dist-info/DESCRIPTION.rst
radproc-0.1.4.dist-info/METADATA
radproc-0.1.4.dist-info/RECORD
radproc-0.1.4.dist-info/WHEEL
radproc-0.1.4.dist-info/metadata.json
radproc-0.1.4.dist-info/top_level.txt
