Metadata-Version: 2.0
Name: radproc
Version: 0.1.4
Summary: Library for RADOLAN composite processing, analysis and data exchange with ArcGIS.
Home-page: https://github.com/jkreklow/radproc/tree/0.1.4
Author: Jennifer Kreklow
Author-email: kreklow@phygeo.uni-hannover.de
License: MIT
Download-URL: https://github.com/jkreklow/radproc/tree/0.1.4/dist/radproc-0.1.4.tar.gz
Keywords: RADOLAN,weather radar,ArcGIS,precipitation,rainfall
Platform: UNKNOWN
Classifier: Development Status :: 5 - Production/Stable
Classifier: Intended Audience :: Science/Research
Classifier: Intended Audience :: Developers
Classifier: Intended Audience :: Education
Classifier: License :: OSI Approved :: MIT License
Classifier: Programming Language :: Python
Classifier: Programming Language :: Python :: 2
Classifier: Programming Language :: Python :: 2.7
Classifier: Topic :: Scientific/Engineering
Classifier: Topic :: Scientific/Engineering :: Atmospheric Science
Classifier: Topic :: Scientific/Engineering :: GIS
Classifier: Operating System :: POSIX :: Linux
Classifier: Operating System :: MacOS :: MacOS X
Classifier: Operating System :: Microsoft :: Windows
Requires-Dist: numpy
Requires-Dist: pandas
Requires-Dist: tables
